eppidtool/__init__.py
eppidtool/__main__.py
eppidtool/eppid.py
eppidtool/main.py
eppidtool/py.typed
eppidtool-1.2.1.dist-info/METADATA
eppidtool-1.2.1.dist-info/WHEEL
eppidtool-1.2.1.dist-info/entry_points.txt
eppidtool-1.2.1.dist-info/licenses/LICENSE
eppidtool-1.2.1.dist-info/RECORD
