Metadata-Version: 2.1
Name: eppidtool
Version: 1.2.1
Summary: Tool for decoding Dell ePPIDs
Project-URL: Repository, https://github.com/Wer-Wolf/eppidtool
Project-URL: Bugtracker, https://github.com/Wer-Wolf/eppidtool/issues
Author-email: Armin Wolf <W_Armin@gmx.de>
License-File: LICENSE
Keywords: dell,eppid
Classifier: Environment :: Console
Classifier: Intended Audience :: End Users/Desktop
Classifier: License :: OSI Approved :: GNU General Public License v3 (GPLv3)
Classifier: Operating System :: OS Independent
Classifier: Programming Language :: Python :: 3 :: Only
Classifier: Topic :: System :: Hardware
Classifier: Topic :: Utilities
Classifier: Typing :: Typed
Requires-Python: >=3.10
Requires-Dist: base-repr~=1.0.7
Provides-Extra: extra
Requires-Dist: pycountry~=23.12.11; extra == 'extra'
